Metadata-Version: 2.4
Name: pollinations-ru
Version: 1.0.0
Summary: Легкая Python библиотека для работы с Pollinations AI
Author-email: Nikita <your.email@example.com>
Project-URL: Homepage, https://github.com/yourusername/pollinations-simple
Classifier: Programming Language :: Python :: 3
Classifier: License :: OSI Approved :: MIT License
Classifier: Operating System :: OS Independent
Requires-Python: >=3.7
License-File: LICENSE
Requires-Dist: requests>=2.25.0
Dynamic: license-file
